bitbucket/__init__.py
bitbucket/base.py
bitbucket/commits.py
bitbucket/conf.py
bitbucket/constants.py
bitbucket/credentials.py
bitbucket/exceptions.py
bitbucket/fields.py
bitbucket/projects.py
bitbucket/repos.py
bitbucket/serializers.py
bitbucket/service.py
bitbucket/tags.py
bitbucket/urls.py
bitbucket/views.py
tests/__init__.py
tests/conftest.py
tests/settings.py
tests/integration/__init__.py
tests/integration/conftest.py
tests/integration/commits/__init__.py
tests/integration/commits/test_commits.py
tests/integration/projects/__init__.py
tests/integration/projects/test_projects.py
tests/integration/repos/__init__.py
tests/integration/repos/test_repos.py
tests/unit/__init__.py
tests/unit/test_base.py
tests/unit/test_credentials.py
tests/unit/test_fields.py
tests/unit/test_service.py
tests/unit/commits/__init__.py
tests/unit/commits/test_commits.py
tests/unit/commits/test_views.py
tests/unit/projects/__init__.py
tests/unit/projects/test_projects.py
tests/unit/projects/test_views.py
tests/unit/repos/__init__.py
tests/unit/repos/test_repos.py
tests/unit/repos/test_views.py
tests/unit/tags/__init__.py
tests/unit/tags/test_tags.py
katka_bitbucket-1.5.2.dist-info/LICENSE
katka_bitbucket-1.5.2.dist-info/METADATA
katka_bitbucket-1.5.2.dist-info/WHEEL
katka_bitbucket-1.5.2.dist-info/top_level.txt
katka_bitbucket-1.5.2.dist-info/RECORD
