Metadata-Version: 2.1
Name: katka-bitbucket
Version: 1.5.2
Summary: Katka Django application for integration with bitbucket
Home-page: https://github.com/kpn/katka-bitbucket
Author: D-Nitro
Author-email: d-nitro@kpn.com
License: UNKNOWN
Platform: UNKNOWN
Classifier: Development Status :: 3 - Alpha
Classifier: Framework :: Django :: 2.1
Classifier: Intended Audience :: Developers
Classifier: Natural Language :: English
Classifier: Operating System :: OS Independent
Classifier: Programming Language :: Python :: 3.6
Classifier: Topic :: Internet :: WWW/HTTP
Requires-Dist: Django (<3.0,>=2.1)
Requires-Dist: djangorestframework (<4.0.0,>=3.9.0)
Requires-Dist: pkgsettings (<1.0.0,>=0.12.0)
